aggregate_root/__init__.py
aggregate_root/aggregate_root.py
aggregate_root/events.py
aggregate_root/repository.py
aggregate_root-0.1.0.dist-info/METADATA
aggregate_root-0.1.0.dist-info/WHEEL
aggregate_root-0.1.0.dist-info/licenses/LICENSE
aggregate_root-0.1.0.dist-info/RECORD
